lightkit/__init__.py
lightkit/data/__init__.py
lightkit/data/collation.py
lightkit/data/loader.py
lightkit/data/sampler.py
lightkit/data/types.py
lightkit/estimator/__init__.py
lightkit/estimator/_protocols.py
lightkit/estimator/base.py
lightkit/estimator/configurable.py
lightkit/estimator/exception.py
lightkit/estimator/mixins.py
lightkit/nn/__init__.py
lightkit/nn/_protocols.py
lightkit/nn/configurable.py
lightkit/py.typed
lightkit/utils/__init__.py
lightkit/utils/generics.py
lightkit/utils/path.py
lightkit-0.5.0.dist-info/METADATA
lightkit-0.5.0.dist-info/WHEEL
lightkit-0.5.0.dist-info/LICENSE
lightkit-0.5.0.dist-info/RECORD
