Metadata-Version: 2.1
Name: lightkit
Version: 0.5.0
Summary: Utilities for PyTorch and PyTorch Lightning.
Home-page: https://github.com/borchero/lightkit
License: MIT
Author: Oliver Borchert
Author-email: me@borchero.com
Requires-Python: >=3.8,<3.11
Classifier: Development Status :: 4 - Beta
Classifier: License :: OSI Approved :: MIT License
Classifier: Programming Language :: Python :: 3
Classifier: Programming Language :: Python :: 3.8
Classifier: Programming Language :: Python :: 3.9
Classifier: Programming Language :: Python :: 3.10
Classifier: Topic :: Scientific/Engineering :: Artificial Intelligence
Requires-Dist: numpy (>=1.20.0,<2.0.0)
Requires-Dist: pytorch-lightning (>=1.5.8,<2.0.0)
Requires-Dist: torch (>=1.8.0,<1.13.0)
Project-URL: Documentation, https://lightkit.borchero.com
Project-URL: Repository, https://github.com/borchero/lightkit
